setup.cfg
setup.py
scripts/tweesten
tweesten/__init__.py
tweesten/cliparser.py
tweesten/confparser.py
tweesten/imagefetcher.py
tweesten/main.py
tweesten.egg-info/PKG-INFO
tweesten.egg-info/SOURCES.txt
tweesten.egg-info/dependency_links.txt
tweesten.egg-info/requires.txt
tweesten.egg-info/top_level.txt