Metadata-Version: 1.1
Name: tweesten
Version: 0.3.0
Summary: twitter bot to tweet a collage of album covers based on your last.fm scrobbles
Home-page: https://github.com/errebenito/tweesten
Author: Raúl Benito
Author-email: erre.benito@gmail.com
License: GNU GPL v3
Download-URL: https://github.com/errebenito/tweesten/releases/tag/v0.3.0
Platform: UNKNOWN
Classifier: Intended Audience :: End Users/Desktop
Classifier: Environment :: Console
Classifier: License :: OSI Approved :: GNU General Public License (GPL)
Classifier: Operating System :: POSIX :: Linux
Classifier: Programming Language :: Python :: 3.4
